{
  "updated": "2026-07-20T19:15:28.194297+00:00",
  "items": [
    {
      "title": "NEXA Lending and former partner Mat Grella end legal fight",
      "link": "https://www.housingwire.com/articles/nexa-lending-and-former-partner-mat-grella-end-legal-fight/",
      "source": "HousingWire",
      "published": "2026-07-20T18:46:44+00:00",
      "summary": "NEXA Lending CEO Mike Kortas says the settlement ends all Grella lawsuits and gives him 100% ownership of NEXA after years of litigation."
    },
    {
      "title": "Windermere names Diana Wall chief growth officer",
      "link": "https://www.housingwire.com/articles/windermere-diana-wall-growth-officer/",
      "source": "HousingWire",
      "published": "2026-07-20T18:37:07+00:00",
      "summary": "Windermere created a chief growth officer role, hiring Diana Wall to lead franchise growth, M&#038;A, and market entry across its platform."
    },
    {
      "title": "Behind closed doors: The next phase of Compass\u2019s Code of Ethics complaints against Zillow",
      "link": "https://www.housingwire.com/articles/nar-code-ethics-complaints-process/",
      "source": "HousingWire",
      "published": "2026-07-20T18:30:54+00:00",
      "summary": "Compass filed ethics complaints against Zillow across 26 states, raising focus on confidentiality, hearings, discipline, and appeals."
    },
    {
      "title": "Starter home inventory trails 2019 by 300,000 listings, per new data",
      "link": "https://www.housingwire.com/articles/starter-home-inventory-down-300000-from-2019/",
      "source": "HousingWire",
      "published": "2026-07-20T18:27:08+00:00",
      "summary": "Realtor.com finds the U.S. starter home market still short 300,000 listings vs. 2019 and buyers now need $78,000 income to purchase."
    },
    {
      "title": "He Started with $5,000. Now He Owns 14 Rental Properties (And Quit His Job!)",
      "link": "https://www.biggerpockets.com/blog/real-estate-1306",
      "source": "BiggerPockets Blog",
      "published": "2026-07-20T11:00:30+00:00",
      "summary": "When Niyi Adewole got his first \u201creal\u201d job out of college, he had one goal: financial freedom. But when he asked his coworkers about the company 401(k), he left more [&#8230;]"
    },
    {
      "title": "The biggest mistake sellers are making right now (and how you can help them avoid it)",
      "link": "https://www.inman.com/2026/07/19/the-biggest-mistake-sellers-are-making-right-now-and-how-you-can-help-them-avoid-it/",
      "source": "Inman",
      "published": "2026-07-19T09:00:50+00:00",
      "summary": "Although you can't control rates, inventory or affordability, Jimmy Burgess writes, you can help your sellers navigate those realities."
    },
    {
      "title": "RealPage acquires Cherre to build the data foundation for AI",
      "link": "https://www.inman.com/2026/07/17/realpage-acquires-cherre/",
      "source": "Inman",
      "published": "2026-07-17T16:29:38+00:00",
      "summary": "RealPage has completed its acquisition of Cherre, betting that real estate's AI ambitions hinge on cleaner, governed data across the capital stack."
    },
    {
      "title": "BPCON 2026: Your Complete Guide to Our Biggest Event of the Year",
      "link": "https://www.biggerpockets.com/blog/guide-to-bpcon-2026",
      "source": "BiggerPockets Blog",
      "published": "2026-07-17T15:58:08+00:00",
      "summary": "From the perspective of the BPCON Planner, who is also an investor and obsessed with helping people find their people to achieve their financial independence goals. Key Takeaways BPCON is [&#8230;]"
    },
    {
      "title": "\u2018You\u2019re all Tony Stark\u2019: Rechat exec on AI and the Iron Man mindset",
      "link": "https://www.inman.com/2026/07/17/rechat-exec-ai-real-estate/",
      "source": "Inman",
      "published": "2026-07-17T15:32:53+00:00",
      "summary": "Rechat's Audie Chamberlain discusses how AI can cut weeks of marketing work into minutes, why \"AI-powered\" has become a meaningless term, and how to build an AI \"chief of staff.\""
    },
    {
      "title": "Here\u2019s How the New 21st Century ROAD to Housing Act Could Help Real Estate Investors",
      "link": "https://www.biggerpockets.com/blog/how-the-21st-century-road-to-housing-act-could-help-real-estate-investors",
      "source": "BiggerPockets Blog",
      "published": "2026-07-17T14:31:53+00:00",
      "summary": "Although the recently passed 21st Century ROAD to Housing Act is primarily aimed at first-time homebuyers, it also benefits investors when applied correctly. The changes might not be immediate, but [&"
    },
    {
      "title": "Winning AI search: Now Streaming",
      "link": "https://www.inman.com/2026/07/17/winning-ai-search-now-streaming/",
      "source": "Inman",
      "published": "2026-07-17T13:55:14+00:00",
      "summary": "Jeff Lobb of SparkTank Media and Searchably.ai teaches you\u00a0how to get discovered by AI as online search shifts."
    },
    {
      "title": "The Housing Market Is Shifting. Here\u2019s What Rookies Should Do. (Rookie Reply)",
      "link": "https://www.biggerpockets.com/blog/rookie-745",
      "source": "BiggerPockets Blog",
      "published": "2026-07-17T11:00:46+00:00",
      "summary": "The housing market looks very different than it did just a year or two ago. Home prices are softening, rates have eased slightly from the highs of 2023 and 2024, [&#8230;]"
    },
    {
      "title": "Best HELOC Lenders in 2026: Full Comparison Guide",
      "link": "https://themortgagereports.com/128311/best-heloc-lenders",
      "source": "The Mortgage Reports",
      "published": "2026-07-14T12:00:00+00:00",
      "summary": "Best HELOC lenders include Aven for fast approvals, Navy Federal for 95% LTV, Bank of America for low fees, and PNC for scores starting at 600."
    },
    {
      "title": "heloc lender test",
      "link": "https://themortgagereports.com/133135/133135",
      "source": "The Mortgage Reports",
      "published": "2026-07-07T21:47:43+00:00",
      "summary": "Key Takeaways Tapping your home equity through a HELOC can be one of the most affordable ways to borrow, but the lender you choose affects everything from your interest rate [&#8230;]"
    },
    {
      "title": "Nada Review for 2026: Rates, Loan Options and Customer Feedback",
      "link": "https://themortgagereports.com/132666/nada-review",
      "source": "The Mortgage Reports",
      "published": "2026-06-22T18:08:59+00:00",
      "summary": "Nada lets homeowners access equity without a loan or refinancing. Our Nada review compares costs, requirements, pros, cons, and alternatives."
    },
    {
      "title": "Own Up Review for 2026: Compare Rates, Lenders & Loan Offers",
      "link": "https://themortgagereports.com/132652/own-up-review",
      "source": "The Mortgage Reports",
      "published": "2026-06-22T18:03:37+00:00",
      "summary": "Compare Own Up\u2019s mortgage marketplace, lender network, costs, reviews, and borrower experience to see whether it fits your home loan needs."
    },
    {
      "title": "This is the End and a New Beginning",
      "link": "http://www.blogger.com/feeds/10004977/posts/default/1850858928807080500",
      "source": "Calculated Risk",
      "published": "2026-01-12T08:21:00.005000-05:00",
      "summary": ""
    },
    {
      "title": "Sunday Night Futures",
      "link": "http://www.blogger.com/feeds/10004977/posts/default/7171326054045106871",
      "source": "Calculated Risk",
      "published": "2026-01-11T19:50:00.001000-05:00",
      "summary": ""
    },
    {
      "title": "Hotels: Occupancy Rate Increased 4.4% Year-over-year",
      "link": "http://www.blogger.com/feeds/10004977/posts/default/1428564876758748355",
      "source": "Calculated Risk",
      "published": "2026-01-11T08:12:00.005000-05:00",
      "summary": ""
    },
    {
      "title": "Real Estate Newsletter Articles this Week:Housing Starts Decreased to 1.246 million Annual Rate",
      "link": "http://www.blogger.com/feeds/10004977/posts/default/8311505410682755186",
      "source": "Calculated Risk",
      "published": "2026-01-10T14:11:00.001000-05:00",
      "summary": ""
    }
  ]
}